edms/__init__.py
edms/__main__.py
edms/_version.py
edms/config.py
edms/main.py
edms/utils.py
edms/bio/__init__.py
edms/bio/clone.py
edms/bio/fastq.py
edms/bio/genbank.py
edms/bio/ngs.py
edms/bio/pe.py
edms/bio/pegLIT.py
edms/bio/primedesign.py
edms/bio/qPCR.py
edms/bio/sanger.py
edms/bio/signature.py
edms/bio/transfect.py
edms/dat/__init__.py
edms/dat/cosmic.py
edms/dat/cvar.py
edms/dat/ncbi.py
edms/gen/__init__.py
edms/gen/cli.py
edms/gen/image.py
edms/gen/io.py
edms/gen/plot.py
edms/gen/stat.py
edms/gen/tidy.py
edms/resources/RE_type_IIS.csv
edms/resources/UMI_15_hamming_4_yield_18687_Esp3I_0.csv
edms/resources/UMI_15_hamming_4_yield_19356.csv
edms/resources/edms_pcr.csv
edms/scripts/autocomplete.sh
edms-0.3.1.post0.dist-info/licenses/LICENSE
edms-0.3.1.post0.dist-info/METADATA
edms-0.3.1.post0.dist-info/WHEEL
edms-0.3.1.post0.dist-info/entry_points.txt
edms-0.3.1.post0.dist-info/top_level.txt
edms-0.3.1.post0.dist-info/RECORD
