Metadata-Version: 2.4
Name: edms
Version: 0.3.1.post0
Summary: Endogenous Deep Mutational Scans
Author-email: Marcanthony Zepeda <mzepeda@g.harvard.edu>
License: MIT License
Project-URL: Homepage, https://github.com/marczepeda/edms
Project-URL: Repository, https://github.com/marczepeda/edms
Project-URL: Issues, https://github.com/marczepeda/edms/issues
Project-URL: Documentation, https://github.com/marczepeda/edms#readme
Classifier: Programming Language :: Python :: 3
Classifier: Operating System :: OS Independent
Requires-Python: >=3.11
License-File: LICENSE
Requires-Dist: numpy
Requires-Dist: matplotlib
Requires-Dist: seaborn
Requires-Dist: pandas
Requires-Dist: biopython
Requires-Dist: requests
Requires-Dist: scipy
Requires-Dist: statsmodels
Requires-Dist: scikit-learn
Requires-Dist: Levenshtein
Requires-Dist: ViennaRNA
Requires-Dist: adjustText
Requires-Dist: pillow
Requires-Dist: dna-features-viewer
Requires-Dist: openpyxl
Requires-Dist: psutil
Requires-Dist: argcomplete
Requires-Dist: rich
Requires-Dist: rich-argparse
Dynamic: license-file
